comport/__init__.py
comport/py.typed
comport-0.0.1.dist-info/METADATA
comport-0.0.1.dist-info/WHEEL
comport-0.0.1.dist-info/RECORD
